{"code":200,"status":"Ok","etag":"9f3a61fc0c06eae1764fe63a95596bc8d01283d0","data":{"offset":1275,"limit":5,"total":1402,"count":5,"results":[{"id":1009682,"name":"U.S. Agent","description":"With the end of the Vietnam War, John Walker thought his dreams of becoming a war hero had also ended, until he learned of the Power Broker, who could give anyone superhuman powers, which Walker used to first become Super-Patriot and later, U.S. Agent.","modified":"1969-12-31T19:00:00-0500","thumbnail":{"path":"http://i.annihil.us/u/prod/marvel/i/mg/8/b0/4c003a8f16b6b","extension":"jpg"},"resourceURI":"http://gateway.marvel.com/v1/public/characters/1009682","comics":{"available":32,"collectionURI":"http://gateway.marvel.com/v1/public/characters/1009682/comics","items":[{"resourceURI":"http://gateway.marvel.com/v1/public/comics/12642","name":"Alpha Flight (1983) #103"},{"resourceURI":"http://gateway.marvel.com/v1/public/comics/17787","name":"Avengers West Coast (1985) #100"},{"resourceURI":"http://gateway.marvel.com/v1/public/comics/12793","name":"Captain America (1998) #33"},{"resourceURI":"http://gateway.marvel.com/v1/public/comics/7739","name":"Captain America (1968) #358"},{"resourceURI":"http://gateway.marvel.com/v1/public/comics/7740","name":"Captain America (1968) #359"},{"resourceURI":"http://gateway.marvel.com/v1/public/comics/7741","name":"Captain America (1968) #360"},{"resourceURI":"http://gateway.marvel.com/v1/public/comics/7742","name":"Captain America (1968) #361"},{"resourceURI":"http://gateway.marvel.com/v1/public/comics/7743","name":"Captain America (1968) #362"},{"resourceURI":"http://gateway.marvel.com/v1/public/comics/7761","name":"Captain America (1968) #380"},{"resourceURI":"http://gateway.marvel.com/v1/public/comics/7762","name":"Captain America (1968) #381"},{"resourceURI":"http://gateway.marvel.com/v1/public/comics/7763","name":"Captain America (1968) #382"},{"resourceURI":"http://gateway.marvel.com/v1/public/comics/7764","name":"Captain America (1968) #383"},{"resourceURI":"http://gateway.marvel.com/v1/public/comics/33346","name":"Captain America (2004) #606 (HEROIC AGE VARIANT)"},{"resourceURI":"http://gateway.marvel.com/v1/public/comics/36951","name":"Captain America Corps (2010) #2"},{"resourceURI":"http://gateway.marvel.com/v1/public/comics/36950","name":"Captain America Corps (2010) #3"},{"resourceURI":"http://gateway.marvel.com/v1/public/comics/30015","name":"Incredible Hulks (2009) #607 (MCGUINNESS VARIANT)"},{"resourceURI":"http://gateway.marvel.com/v1/public/comics/9569","name":"Iron Man (1968) #317"},{"resourceURI":"http://gateway.marvel.com/v1/public/comics/10016","name":"Marvel Comics Presents (1988) #104"},{"resourceURI":"http://gateway.marvel.com/v1/public/comics/15524","name":"Marvel Super-Heroes (1992) #8"},{"resourceURI":"http://gateway.marvel.com/v1/public/comics/1903","name":"Marvel Visionaries: Steve Ditko (Hardcover)"}],"returned":20},"series":{"available":12,"collectionURI":"http://gateway.marvel.com/v1/public/characters/1009682/series","items":[{"resourceURI":"http://gateway.marvel.com/v1/public/series/2116","name":"Alpha Flight (1983 - 1994)"},{"resourceURI":"http://gateway.marvel.com/v1/public/series/3623","name":"Avengers West Coast (1985 - 1994)"},{"resourceURI":"http://gateway.marvel.com/v1/public/series/832","name":"Captain America (2004 - 2011)"},{"resourceURI":"http://gateway.marvel.com/v1/public/series/1997","name":"Captain America (1998 - 2002)"},{"resourceURI":"http://gateway.marvel.com/v1/public/series/1996","name":"Captain America (1968 - 1996)"},{"resourceURI":"http://gateway.marvel.com/v1/public/series/13199","name":"Captain America Corps (2010 - 2011)"},{"resourceURI":"http://gateway.marvel.com/v1/public/series/8842","name":"Incredible Hulks (2009 - 2011)"},{"resourceURI":"http://gateway.marvel.com/v1/public/series/2029","name":"Iron Man (1968 - 1996)"},{"resourceURI":"http://gateway.marvel.com/v1/public/series/2039","name":"Marvel Comics Presents (1988 - 1995)"},{"resourceURI":"http://gateway.marvel.com/v1/public/series/2301","name":"Marvel Super-Heroes (1992 - 1993)"},{"resourceURI":"http://gateway.marvel.com/v1/public/series/1504","name":"Marvel Visionaries: Steve Ditko (2005)"},{"resourceURI":"http://gateway.marvel.com/v1/public/series/1866","name":"Mighty Avengers (2007 - 2010)"}],"returned":12},"stories":{"available":33,"collectionURI":"http://gateway.marvel.com/v1/public/characters/1009682/stories","items":[{"resourceURI":"http://gateway.marvel.com/v1/public/stories/17986","name":"Captain America (1968) #358","type":"interiorStory"},{"resourceURI":"http://gateway.marvel.com/v1/public/stories/17987","name":"Siege","type":""},{"resourceURI":"http://gateway.marvel.com/v1/public/stories/17990","name":"Death Calling","type":""},{"resourceURI":"http://gateway.marvel.com/v1/public/stories/17992","name":"Captain America (1968) #360","type":"interiorStory"},{"resourceURI":"http://gateway.marvel.com/v1/public/stories/17993","name":"Conflagration","type":""},{"resourceURI":"http://gateway.marvel.com/v1/public/stories/17996","name":"Augmentation","type":""},{"resourceURI":"http://gateway.marvel.com/v1/public/stories/17999","name":"Won't Get Scourged Again","type":""},{"resourceURI":"http://gateway.marvel.com/v1/public/stories/18052","name":"The Unremembered Past","type":""},{"resourceURI":"http://gateway.marvel.com/v1/public/stories/18055","name":"Ask Not What Your Country Can Do For You","type":""},{"resourceURI":"http://gateway.marvel.com/v1/public/stories/18058","name":"Thanks For the Memories","type":""},{"resourceURI":"http://gateway.marvel.com/v1/public/stories/18062","name":"Man of Straw","type":""},{"resourceURI":"http://gateway.marvel.com/v1/public/stories/19616","name":"Vicious Circle (3 of 3)","type":"cover"},{"resourceURI":"http://gateway.marvel.com/v1/public/stories/21108","name":"Spontaneous Combustion","type":"interiorStory"},{"resourceURI":"http://gateway.marvel.com/v1/public/stories/22708","name":"Fight the Right Thing","type":""},{"resourceURI":"http://gateway.marvel.com/v1/public/stories/31637","name":"Leftovers","type":"interiorStory"},{"resourceURI":"http://gateway.marvel.com/v1/public/stories/37790","name":"Boys Will Be Boys","type":""},{"resourceURI":"http://gateway.marvel.com/v1/public/stories/52267","name":"2 of 6","type":"interiorStory"},{"resourceURI":"http://gateway.marvel.com/v1/public/stories/52726","name":"3 of 6","type":"interiorStory"},{"resourceURI":"http://gateway.marvel.com/v1/public/stories/53148","name":"1 of 1","type":"interiorStory"},{"resourceURI":"http://gateway.marvel.com/v1/public/stories/53543","name":"1 of 2","type":"interiorStory"}],"returned":20},"events":{"available":2,"collectionURI":"http://gateway.marvel.com/v1/public/characters/1009682/events","items":[{"resourceURI":"http://gateway.marvel.com/v1/public/events/318","name":"Dark Reign"},{"resourceURI":"http://gateway.marvel.com/v1/public/events/273","name":"Siege"}],"returned":2},"urls":[{"type":"detail","url":"http://marvel.com/comics/characters/1009682/us_agent?utm_campaign=apiRef&utm_source=51053776bff9f684b08a41a47734167b"},{"type":"wiki","url":"http://marvel.com/universe/U.S.Agent?utm_campaign=apiRef&utm_source=51053776bff9f684b08a41a47734167b"}]},{"id":1009683,"name":"Uatu The Watcher","description":"Uatu grew so fond of the lifeforms he observed that he occasionally violated his vow of non-interference when Earth's existence was threatened.","modified":"2013-12-26T14:55:54-0500","thumbnail":{"path":"http://i.annihil.us/u/prod/marvel/i/mg/9/03/5274135912e8d","extension":"jpg"},"resourceURI":"http://gateway.marvel.com/v1/public/characters/1009683","comics":{"available":30,"collectionURI":"http://gateway.marvel.com/v1/public/characters/1009683/comics","items":[{"resourceURI":"http://gateway.marvel.com/v1/public/comics/36952","name":"Captain America Corps (2010) #1"},{"resourceURI":"http://gateway.marvel.com/v1/public/comics/8464","name":"Deadpool (1997) #11"},{"resourceURI":"http://gateway.marvel.com/v1/public/comics/8478","name":"Deadpool (1997) #24"},{"resourceURI":"http://gateway.marvel.com/v1/public/comics/36004","name":"Deadpool Team-Up (2010) #884"},{"resourceURI":"http://gateway.marvel.com/v1/public/comics/41028","name":"Deadpool Team-Up Vol. 3 (Hardcover)"},{"resourceURI":"http://gateway.marvel.com/v1/public/comics/15567","name":"Fantastic Four (1998) #46"},{"resourceURI":"http://gateway.marvel.com/v1/public/comics/15570","name":"Fantastic Four (1998) #49"},{"resourceURI":"http://gateway.marvel.com/v1/public/comics/13181","name":"Fantastic Four (1961) #358"},{"resourceURI":"http://gateway.marvel.com/v1/public/comics/13193","name":"Fantastic Four (1961) #369"},{"resourceURI":"http://gateway.marvel.com/v1/public/comics/13196","name":"Fantastic Four (1961) #371"},{"resourceURI":"http://gateway.marvel.com/v1/public/comics/13199","name":"Fantastic Four (1961) #374"},{"resourceURI":"http://gateway.marvel.com/v1/public/comics/13200","name":"Fantastic Four (1961) #375"},{"resourceURI":"http://gateway.marvel.com/v1/public/comics/13213","name":"Fantastic Four (1961) #387"},{"resourceURI":"http://gateway.marvel.com/v1/public/comics/13214","name":"Fantastic Four (1961) #388"},{"resourceURI":"http://gateway.marvel.com/v1/public/comics/13215","name":"Fantastic Four (1961) #389"},{"resourceURI":"http://gateway.marvel.com/v1/public/comics/13217","name":"Fantastic Four (1961) #390"},{"resourceURI":"http://gateway.marvel.com/v1/public/comics/13218","name":"Fantastic Four (1961) #391"},{"resourceURI":"http://gateway.marvel.com/v1/public/comics/13219","name":"Fantastic Four (1961) #392"},{"resourceURI":"http://gateway.marvel.com/v1/public/comics/13220","name":"Fantastic Four (1961) #393"},{"resourceURI":"http://gateway.marvel.com/v1/public/comics/13223","name":"Fantastic Four (1961) #396"}],"returned":20},"series":{"available":10,"collectionURI":"http://gateway.marvel.com/v1/public/characters/1009683/series","items":[{"resourceURI":"http://gateway.marvel.com/v1/public/series/13199","name":"Captain America Corps (2010 - 2011)"},{"resourceURI":"http://gateway.marvel.com/v1/public/series/2005","name":"Deadpool (1997 - 2002)"},{"resourceURI":"http://gateway.marvel.com/v1/public/series/11518","name":"Deadpool Team-Up (2010 - 2011)"},{"resourceURI":"http://gateway.marvel.com/v1/public/series/12988","name":"Deadpool Team-Up Vol. 3 (2010 - Present)"},{"resourceURI":"http://gateway.marvel.com/v1/public/series/421","name":"Fantastic Four (1998 - 2012)"},{"resourceURI":"http://gateway.marvel.com/v1/public/series/2121","name":"Fantastic Four (1961 - 1998)"},{"resourceURI":"http://gateway.marvel.com/v1/public/series/1814","name":"Heroes Reborn: Iron Man (2006)"},{"resourceURI":"http://gateway.marvel.com/v1/public/series/13577","name":"Iron Man (1996 - 1998)"},{"resourceURI":"http://gateway.marvel.com/v1/public/series/15297","name":"Point One (2011)"},{"resourceURI":"http://gateway.marvel.com/v1/public/series/581","name":"Thor (1998 - 2004)"}],"returned":10},"stories":{"available":31,"collectionURI":"http://gateway.marvel.com/v1/public/characters/1009683/stories","items":[{"resourceURI":"http://gateway.marvel.com/v1/public/stories/13040","name":"[The Watcher]","type":"pinup"},{"resourceURI":"http://gateway.marvel.com/v1/public/stories/13113","name":"With Malice Toward All!","type":"interiorStory"},{"resourceURI":"http://gateway.marvel.com/v1/public/stories/13127","name":"This Flame, This Fury","type":"interiorStory"},{"resourceURI":"http://gateway.marvel.com/v1/public/stories/13145","name":"Suddenly ... The Secret Defenders","type":"interiorStory"},{"resourceURI":"http://gateway.marvel.com/v1/public/stories/13151","name":"It's Always Darkest Before the ... DOOM!","type":"interiorStory"},{"resourceURI":"http://gateway.marvel.com/v1/public/stories/13231","name":"Nobody Gets Out Alive!","type":"interiorStory"},{"resourceURI":"http://gateway.marvel.com/v1/public/stories/13237","name":"Deadly Is the Dark Raider","type":"interiorStory"},{"resourceURI":"http://gateway.marvel.com/v1/public/stories/13244","name":"Behold a Fatal Future!","type":"interiorStory"},{"resourceURI":"http://gateway.marvel.com/v1/public/stories/13251","name":"The Coming of Galactus!","type":"cover"},{"resourceURI":"http://gateway.marvel.com/v1/public/stories/13252","name":"\"Past Deceptions and Future Lies!\"","type":"interiorStory"},{"resourceURI":"http://gateway.marvel.com/v1/public/stories/13259","name":"If Death Be Our Destiny--!","type":"interiorStory"},{"resourceURI":"http://gateway.marvel.com/v1/public/stories/13265","name":"The Final Gantlet!","type":"interiorStory"},{"resourceURI":"http://gateway.marvel.com/v1/public/stories/13271","name":"Days of Recent Past","type":"interiorStory"},{"resourceURI":"http://gateway.marvel.com/v1/public/stories/13293","name":"In Search of Doom!","type":"interiorStory"},{"resourceURI":"http://gateway.marvel.com/v1/public/stories/13300","name":"Resurrection!","type":"interiorStory"},{"resourceURI":"http://gateway.marvel.com/v1/public/stories/13308","name":"Watchers Lie!","type":"interiorStory"},{"resourceURI":"http://gateway.marvel.com/v1/public/stories/13332","name":"Even the Watchers Can Die!","type":"interiorStory"},{"resourceURI":"http://gateway.marvel.com/v1/public/stories/24527","name":"Deadpool (1997) #11","type":"interiorStory"},{"resourceURI":"http://gateway.marvel.com/v1/public/stories/24567","name":"Deadpool (1997) #24","type":"interiorStory"},{"resourceURI":"http://gateway.marvel.com/v1/public/stories/31804","name":"It's Too Late to Stop Now!","type":"interiorStory"}],"returned":20},"events":{"available":1,"collectionURI":"http://gateway.marvel.com/v1/public/characters/1009683/events","items":[{"resourceURI":"http://gateway.marvel.com/v1/public/events/29","name":"Infinity War"}],"returned":1},"urls":[{"type":"detail","url":"http://marvel.com/comics/characters/1009683/uatu_the_watcher?utm_campaign=apiRef&utm_source=51053776bff9f684b08a41a47734167b"},{"type":"wiki","url":"http://marvel.com/universe/Uatu_the_Watcher?utm_campaign=apiRef&utm_source=51053776bff9f684b08a41a47734167b"}]},{"id":1010358,"name":"Ulik","description":"Ulik was a Rock Troll from the realm known as Nornheim, located underground within the dimension of Asgard.","modified":"2011-01-25T16:05:37-0500","thumbnail":{"path":"http://i.annihil.us/u/prod/marvel/i/mg/3/c0/4d3f3b2078758","extension":"jpg"},"resourceURI":"http://gateway.marvel.com/v1/public/characters/1010358","comics":{"available":19,"collectionURI":"http://gateway.marvel.com/v1/public/characters/1010358/comics","items":[{"resourceURI":"http://gateway.marvel.com/v1/public/comics/33861","name":"Iron Man/Thor (2010) #3"},{"resourceURI":"http://gateway.marvel.com/v1/public/comics/37753","name":"Journey Into Mystery (1996) #509"},{"resourceURI":"http://gateway.marvel.com/v1/public/comics/37755","name":"Journey Into Mystery (1996) #512"},{"resourceURI":"http://gateway.marvel.com/v1/public/comics/16055","name":"Marvel Knights (2000) #1"},{"resourceURI":"http://gateway.marvel.com/v1/public/comics/16062","name":"Marvel Knights (2000) #2"},{"resourceURI":"http://gateway.marvel.com/v1/public/comics/16063","name":"Marvel Knights (2000) #3"},{"resourceURI":"http://gateway.marvel.com/v1/public/comics/18636","name":"Thor (1998) #14"},{"resourceURI":"http://gateway.marvel.com/v1/public/comics/18643","name":"Thor (1998) #20"},{"resourceURI":"http://gateway.marvel.com/v1/public/comics/18645","name":"Thor (1998) #22"},{"resourceURI":"http://gateway.marvel.com/v1/public/comics/18658","name":"Thor (1998) #34"},{"resourceURI":"http://gateway.marvel.com/v1/public/comics/18659","name":"Thor (1998) #35"},{"resourceURI":"http://gateway.marvel.com/v1/public/comics/18667","name":"Thor (1998) #42"},{"resourceURI":"http://gateway.marvel.com/v1/public/comics/11501","name":"Thor (1966) #173"},{"resourceURI":"http://gateway.marvel.com/v1/public/comics/11538","name":"Thor (1966) #210"},{"resourceURI":"http://gateway.marvel.com/v1/public/comics/11539","name":"Thor (1966) #211"},{"resourceURI":"http://gateway.marvel.com/v1/public/comics/11545","name":"Thor (1966) #217"},{"resourceURI":"http://gateway.marvel.com/v1/public/comics/16674","name":"Thor Annual (1966) #13"},{"resourceURI":"http://gateway.marvel.com/v1/public/comics/16676","name":"Thor Annual (1966) #15"},{"resourceURI":"http://gateway.marvel.com/v1/public/comics/1073","name":"Thor Vol. I: Death of Odin (Trade Paperback)"}],"returned":19},"series":{"available":7,"collectionURI":"http://gateway.marvel.com/v1/public/characters/1010358/series","items":[{"resourceURI":"http://gateway.marvel.com/v1/public/series/10725","name":"Iron Man/Thor (2010 - 2011)"},{"resourceURI":"http://gateway.marvel.com/v1/public/series/13569","name":"Journey Into Mystery (1996 - 1998)"},{"resourceURI":"http://gateway.marvel.com/v1/public/series/2576","name":"Marvel Knights (2000 - 2001)"},{"resourceURI":"http://gateway.marvel.com/v1/public/series/2083","name":"Thor (1966 - 1996)"},{"resourceURI":"http://gateway.marvel.com/v1/public/series/581","name":"Thor (1998 - 2004)"},{"resourceURI":"http://gateway.marvel.com/v1/public/series/2978","name":"Thor Annual (1966 - 2001)"},{"resourceURI":"http://gateway.marvel.com/v1/public/series/133","name":"Thor Vol. I: Death of Odin (1999)"}],"returned":7},"stories":{"available":21,"collectionURI":"http://gateway.marvel.com/v1/public/characters/1010358/stories","items":[{"resourceURI":"http://gateway.marvel.com/v1/public/stories/16622","name":"Thor (1966) #173","type":"interiorStory"},{"resourceURI":"http://gateway.marvel.com/v1/public/stories/16697","name":"Thor (1966) #210","type":"interiorStory"},{"resourceURI":"http://gateway.marvel.com/v1/public/stories/16699","name":"Thor (1966) #211","type":"interiorStory"},{"resourceURI":"http://gateway.marvel.com/v1/public/stories/16711","name":"Thor (1966) #217","type":"interiorStory"},{"resourceURI":"http://gateway.marvel.com/v1/public/stories/32752","name":"The Burrowers","type":"interiorStory"},{"resourceURI":"http://gateway.marvel.com/v1/public/stories/32763","name":"Thunder Below","type":"interiorStory"},{"resourceURI":"http://gateway.marvel.com/v1/public/stories/32764","name":"Cover #32764","type":"cover"},{"resourceURI":"http://gateway.marvel.com/v1/public/stories/32765","name":"The Destroyers","type":"interiorStory"},{"resourceURI":"http://gateway.marvel.com/v1/public/stories/33957","name":"Cover #33957","type":"cover"},{"resourceURI":"http://gateway.marvel.com/v1/public/stories/33958","name":"And Evil Shall Inherit","type":"interiorStory"},{"resourceURI":"http://gateway.marvel.com/v1/public/stories/33970","name":"Pin-Up","type":"pinup"},{"resourceURI":"http://gateway.marvel.com/v1/public/stories/39927","name":"Hammer Time!","type":"interiorStory"},{"resourceURI":"http://gateway.marvel.com/v1/public/stories/39948","name":"Thor (1998) #20","type":"interiorStory"},{"resourceURI":"http://gateway.marvel.com/v1/public/stories/39952","name":"Cover #39952","type":"cover"},{"resourceURI":"http://gateway.marvel.com/v1/public/stories/39953","name":"Thor (1998) #22","type":"interiorStory"},{"resourceURI":"http://gateway.marvel.com/v1/public/stories/39982","name":"Man of Tomorrow","type":"interiorStory"},{"resourceURI":"http://gateway.marvel.com/v1/public/stories/39984","name":"Across All Worlds","type":"interiorStory"},{"resourceURI":"http://gateway.marvel.com/v1/public/stories/40001","name":"Taking Charge: Part 2 of 3","type":"interiorStory"},{"resourceURI":"http://gateway.marvel.com/v1/public/stories/76311","name":"Cover From Iron Man/Thor (2010) #3","type":"cover"},{"resourceURI":"http://gateway.marvel.com/v1/public/stories/94920","name":"Journey Into Mystery (1996) #509","type":"cover"}],"returned":20},"events":{"available":0,"collectionURI":"http://gateway.marvel.com/v1/public/characters/1010358/events","items":[],"returned":0},"urls":[{"type":"detail","url":"http://marvel.com/comics/characters/1010358/ulik?utm_campaign=apiRef&utm_source=51053776bff9f684b08a41a47734167b"},{"type":"wiki","url":"http://marvel.com/universe/Ulik?utm_campaign=apiRef&utm_source=51053776bff9f684b08a41a47734167b"}]},{"id":1016825,"name":"Ultimate Spider-Man (USM)","description":"For the past year, Peter Parker has been saving New York City from villains as the masked hero, Spider-Man. Facing thugs and evil geniuses alike, he learns how to balance heroics with homework and friends. Despite being a Super Hero, Peter is very much an average 16-year-old.  With the added responsibilities of being Spider-Man, juggling all the aspects of his life will continually challenge him.                                                                 \r\n\r\nWhen S.H.I.E.L.D. Director, Nick Fury, offers Peter the chance to raise his game and become THE ULTIMATE SPIDER-MAN, Midtown High becomes a secret operations base for Spider-Man and other young heroes under the watchful eye of Fury and the school’s new principal, Agent Coulson. ","modified":"2013-09-18T15:54:46-0400","thumbnail":{"path":"http://i.annihil.us/u/prod/marvel/i/mg/2/50/5232171a451bb","extension":"jpg"},"resourceURI":"http://gateway.marvel.com/v1/public/characters/1016825","comics":{"available":0,"collectionURI":"http://gateway.marvel.com/v1/public/characters/1016825/comics","items":[],"returned":0},"series":{"available":0,"collectionURI":"http://gateway.marvel.com/v1/public/characters/1016825/series","items":[],"returned":0},"stories":{"available":0,"collectionURI":"http://gateway.marvel.com/v1/public/characters/1016825/stories","items":[],"returned":0},"events":{"available":0,"collectionURI":"http://gateway.marvel.com/v1/public/characters/1016825/events","items":[],"returned":0},"urls":[{"type":"detail","url":"http://marvel.com/comics/characters/1016825/ultimate_spider-man_usm?utm_campaign=apiRef&utm_source=51053776bff9f684b08a41a47734167b"},{"type":"wiki","url":"http://marvel.com/universe/?utm_campaign=apiRef&utm_source=51053776bff9f684b08a41a47734167b"}]},{"id":1010803,"name":"Ultimates","description":"","modified":"2011-05-17T17:26:18-0400","thumbnail":{"path":"http://i.annihil.us/u/prod/marvel/i/mg/2/04/4dd2e7ded884f","extension":"jpg"},"resourceURI":"http://gateway.marvel.com/v1/public/characters/1010803","comics":{"available":26,"collectionURI":"http://gateway.marvel.com/v1/public/characters/1010803/comics","items":[{"resourceURI":"http://gateway.marvel.com/v1/public/comics/1282","name":"The Ultimates Vol. 2: Homeland Security (Trade Paperback)"},{"resourceURI":"http://gateway.marvel.com/v1/public/comics/35582","name":"Ultimate Comics Avengers Vs New Ultimates (2010) #1"},{"resourceURI":"http://gateway.marvel.com/v1/public/comics/39343","name":"Ultimate Comics Avengers Vs New Ultimates (2010) #1 (2nd Printing Variant)"},{"resourceURI":"http://gateway.marvel.com/v1/public/comics/36129","name":"Ultimate Comics Avengers Vs New Ultimates (2010) #2"},{"resourceURI":"http://gateway.marvel.com/v1/public/comics/38503","name":"Ultimate Comics Avengers Vs New Ultimates (2010) #2 (HITCH VARIANT)"},{"resourceURI":"http://gateway.marvel.com/v1/public/comics/40246","name":"Ultimate Comics Avengers Vs New Ultimates (2010) #2 (2nd Printing Variant)"},{"resourceURI":"http://gateway.marvel.com/v1/public/comics/36349","name":"Ultimate Comics Avengers Vs New Ultimates (2010) #3"},{"resourceURI":"http://gateway.marvel.com/v1/public/comics/38500","name":"Ultimate Comics Avengers Vs New Ultimates (2010) #3 (CHO VARIANT)"},{"resourceURI":"http://gateway.marvel.com/v1/public/comics/40245","name":"Ultimate Comics Avengers Vs New Ultimates (2010) #3 (2nd Printing Variant)"},{"resourceURI":"http://gateway.marvel.com/v1/public/comics/36127","name":"Ultimate Comics Avengers Vs New Ultimates (2010) #4"},{"resourceURI":"http://gateway.marvel.com/v1/public/comics/38502","name":"Ultimate Comics Avengers Vs New Ultimates (2010) #4 (HITCH VARIANT)"},{"resourceURI":"http://gateway.marvel.com/v1/public/comics/36350","name":"Ultimate Comics Avengers Vs New Ultimates (2010) #5"},{"resourceURI":"http://gateway.marvel.com/v1/public/comics/36125","name":"Ultimate Comics Avengers Vs New Ultimates (2010) #6"},{"resourceURI":"http://gateway.marvel.com/v1/public/comics/38501","name":"Ultimate Comics Avengers Vs New Ultimates (2010) #6 (Hitch Variant)"},{"resourceURI":"http://gateway.marvel.com/v1/public/comics/39468","name":"Ultimate Comics Avengers Vs. New Ultimates (Hardcover)"},{"resourceURI":"http://gateway.marvel.com/v1/public/comics/28946","name":"ULTIMATE COMICS NEW ULTIMATES: THOR REBORN PREMIERE HC (Hardcover)"},{"resourceURI":"http://gateway.marvel.com/v1/public/comics/37520","name":"Ultimate Comics Spider-Man (2009) #150 (WRAPAROUND VARIANT)"},{"resourceURI":"http://gateway.marvel.com/v1/public/comics/16518","name":"Ultimate Power (2006) #9"},{"resourceURI":"http://gateway.marvel.com/v1/public/comics/39358","name":"Ultimate Six (Hardcover)"},{"resourceURI":"http://gateway.marvel.com/v1/public/comics/255","name":"Ultimates (2002) #12"}],"returned":20},"series":{"available":12,"collectionURI":"http://gateway.marvel.com/v1/public/characters/1010803/series","items":[{"resourceURI":"http://gateway.marvel.com/v1/public/series/334","name":"The Ultimates Vol. 2: Homeland Security (2004)"},{"resourceURI":"http://gateway.marvel.com/v1/public/series/12615","name":"Ultimate Comics Avengers Vs New Ultimates (2010 - 2011)"},{"resourceURI":"http://gateway.marvel.com/v1/public/series/14423","name":"Ultimate Comics Avengers Vs. New Ultimates (2011 - Present)"},{"resourceURI":"http://gateway.marvel.com/v1/public/series/10532","name":"ULTIMATE COMICS NEW ULTIMATES: THOR REBORN PREMIERE HC (2011)"},{"resourceURI":"http://gateway.marvel.com/v1/public/series/8509","name":"Ultimate Comics Spider-Man (2009 - 2012)"},{"resourceURI":"http://gateway.marvel.com/v1/public/series/1124","name":"Ultimate Power (2006 - 2008)"},{"resourceURI":"http://gateway.marvel.com/v1/public/series/14313","name":"Ultimate Six (2011 - Present)"},{"resourceURI":"http://gateway.marvel.com/v1/public/series/664","name":"Ultimates (2002 - 2003)"},{"resourceURI":"http://gateway.marvel.com/v1/public/series/709","name":"Ultimates 2 (2004 - 2006)"},{"resourceURI":"http://gateway.marvel.com/v1/public/series/1178","name":"Ultimates 2 Vol. 1: Gods and Monsters (2005)"},{"resourceURI":"http://gateway.marvel.com/v1/public/series/2422","name":"Ultimates 2 Vol. 2: Grand Theft America (2007)"},{"resourceURI":"http://gateway.marvel.com/v1/public/series/1176","name":"Ultimates Vol. 2: Homeland Security (2005)"}],"returned":12},"stories":{"available":17,"collectionURI":"http://gateway.marvel.com/v1/public/characters/1010803/stories","items":[{"resourceURI":"http://gateway.marvel.com/v1/public/stories/2284","name":"Interior #2284","type":"interiorStory"},{"resourceURI":"http://gateway.marvel.com/v1/public/stories/2300","name":"Interior #2300","type":"interiorStory"},{"resourceURI":"http://gateway.marvel.com/v1/public/stories/2733","name":"1 of 1 - The Defenders","type":"cover"},{"resourceURI":"http://gateway.marvel.com/v1/public/stories/2735","name":"1 of 2 - Wedding of the Century","type":"cover"},{"resourceURI":"http://gateway.marvel.com/v1/public/stories/33307","name":"9 of 9 XLS - Ultimate Power","type":"cover"},{"resourceURI":"http://gateway.marvel.com/v1/public/stories/79944","name":"Interior #79944","type":"interiorStory"},{"resourceURI":"http://gateway.marvel.com/v1/public/stories/79945","name":"Cover #79945","type":"cover"},{"resourceURI":"http://gateway.marvel.com/v1/public/stories/79952","name":"Interior #79952","type":"interiorStory"},{"resourceURI":"http://gateway.marvel.com/v1/public/stories/79956","name":"ULTIMATE COMICS AVENGERS VS. NEW ULTIMATES 2","type":"interiorStory"},{"resourceURI":"http://gateway.marvel.com/v1/public/stories/80713","name":"Ultimate Comics Avengers 4 (2010) #3","type":"interiorStory"},{"resourceURI":"http://gateway.marvel.com/v1/public/stories/80714","name":"Ultimate Comics Avengers Vs. New Ultimates #5","type":"cover"},{"resourceURI":"http://gateway.marvel.com/v1/public/stories/82990","name":"Cover #82990","type":"cover"},{"resourceURI":"http://gateway.marvel.com/v1/public/stories/84544","name":"Ultimate Comics Avengers Vs. New Ultimates (2010) #3, CHO VARIANT","type":"interiorStory"},{"resourceURI":"http://gateway.marvel.com/v1/public/stories/89337","name":"Ultimate Six Premiere HC","type":"cover"},{"resourceURI":"http://gateway.marvel.com/v1/public/stories/89558","name":"Interior #89558","type":"interiorStory"},{"resourceURI":"http://gateway.marvel.com/v1/public/stories/90106","name":"ULTIMATE COMICS AVENGERS VS. NEW ULTIMATES 2 HITCH VARIANT","type":"interiorStory"},{"resourceURI":"http://gateway.marvel.com/v1/public/stories/91153","name":"ULTIMATE COMICS AVENGERS VS. NEW ULTIMATES #6 Interior","type":""}],"returned":17},"events":{"available":0,"collectionURI":"http://gateway.marvel.com/v1/public/characters/1010803/events","items":[],"returned":0},"urls":[{"type":"detail","url":"http://marvel.com/comics/characters/1010803/ultimates?utm_campaign=apiRef&utm_source=51053776bff9f684b08a41a47734167b"},{"type":"wiki","url":"http://marvel.com/universe/Ultimates_(Ultimate)?utm_campaign=apiRef&utm_source=51053776bff9f684b08a41a47734167b"}]}]}}