{"code":200,"status":"Ok","etag":"85828b50b75d233717acfe16400717dbf9f431f1","data":{"offset":1270,"limit":5,"total":1402,"count":5,"results":[{"id":1009679,"name":"Tyger Tiger","description":"","modified":"1969-12-31T19:00:00-0500","thumbnail":{"path":"http://i.annihil.us/u/prod/marvel/i/mg/b/40/image_not_available","extension":"jpg"},"resourceURI":"http://gateway.marvel.com/v1/public/characters/1009679","comics":{"available":0,"collectionURI":"http://gateway.marvel.com/v1/public/characters/1009679/comics","items":[],"returned":0},"series":{"available":0,"collectionURI":"http://gateway.marvel.com/v1/public/characters/1009679/series","items":[],"returned":0},"stories":{"available":0,"collectionURI":"http://gateway.marvel.com/v1/public/characters/1009679/stories","items":[],"returned":0},"events":{"available":0,"collectionURI":"http://gateway.marvel.com/v1/public/characters/1009679/events","items":[],"returned":0},"urls":[{"type":"detail","url":"http://marvel.com/comics/characters/1009679/tyger_tiger?utm_campaign=apiRef&utm_source=51053776bff9f684b08a41a47734167b"}]},{"id":1010369,"name":"Typhoid Mary","description":"Typhoid Mary, an enemy and former lover of Daredevil with psionic powers, including telekinesis, is also truly gravely mentally ill and not entirely responsible for her actions.","modified":"2012-01-11T11:47:38-0500","thumbnail":{"path":"http://i.annihil.us/u/prod/marvel/i/mg/1/f0/4c00390aa2403","extension":"jpg"},"resourceURI":"http://gateway.marvel.com/v1/public/characters/1010369","comics":{"available":25,"collectionURI":"http://gateway.marvel.com/v1/public/characters/1010369/comics","items":[{"resourceURI":"http://gateway.marvel.com/v1/public/comics/29317","name":"ACTS OF VENGEANCE CROSSOVERS OMNIBUS (Hardcover)"},{"resourceURI":"http://gateway.marvel.com/v1/public/comics/29318","name":"ACTS OF VENGEANCE CROSSOVERS OMNIBUS (DM Only) (Hardcover)"},{"resourceURI":"http://gateway.marvel.com/v1/public/comics/23968","name":"Avengers: The Initiative (2007) #23"},{"resourceURI":"http://gateway.marvel.com/v1/public/comics/24167","name":"Avengers: The Initiative (2007) #24"},{"resourceURI":"http://gateway.marvel.com/v1/public/comics/36788","name":"Black Panther: The Most Dangerous Man Alive  (2010) #525"},{"resourceURI":"http://gateway.marvel.com/v1/public/comics/15649","name":"Daredevil (1998) #46"},{"resourceURI":"http://gateway.marvel.com/v1/public/comics/15650","name":"Daredevil (1998) #47"},{"resourceURI":"http://gateway.marvel.com/v1/public/comics/15651","name":"Daredevil (1998) #48"},{"resourceURI":"http://gateway.marvel.com/v1/public/comics/8245","name":"Daredevil (1963) #254"},{"resourceURI":"http://gateway.marvel.com/v1/public/comics/8246","name":"Daredevil (1963) #255"},{"resourceURI":"http://gateway.marvel.com/v1/public/comics/8250","name":"Daredevil (1963) #259"},{"resourceURI":"http://gateway.marvel.com/v1/public/comics/8252","name":"Daredevil (1963) #260"},{"resourceURI":"http://gateway.marvel.com/v1/public/comics/8292","name":"Daredevil (1963) #297"},{"resourceURI":"http://gateway.marvel.com/v1/public/comics/1122","name":"Daredevil Vol. 6: Lowlife (Trade Paperback)"},{"resourceURI":"http://gateway.marvel.com/v1/public/comics/1172","name":"Daredevil Vol. 7: Hardcore (Trade Paperback)"},{"resourceURI":"http://gateway.marvel.com/v1/public/comics/8517","name":"Deadpool (1997) #6"},{"resourceURI":"http://gateway.marvel.com/v1/public/comics/8528","name":"Deadpool (1997) #7"},{"resourceURI":"http://gateway.marvel.com/v1/public/comics/8529","name":"Deadpool (1997) #8"},{"resourceURI":"http://gateway.marvel.com/v1/public/comics/8463","name":"Deadpool (1997) #10"},{"resourceURI":"http://gateway.marvel.com/v1/public/comics/8465","name":"Deadpool (1997) #12"}],"returned":20},"series":{"available":12,"collectionURI":"http://gateway.marvel.com/v1/public/characters/1010369/series","items":[{"resourceURI":"http://gateway.marvel.com/v1/public/series/9994","name":"ACTS OF VENGEANCE CROSSOVERS OMNIBUS (2011)"},{"resourceURI":"http://gateway.marvel.com/v1/public/series/9995","name":"ACTS OF VENGEANCE CROSSOVERS OMNIBUS (DM Only) (2011)"},{"resourceURI":"http://gateway.marvel.com/v1/public/series/1945","name":"Avengers: The Initiative (2007 - 2010)"},{"resourceURI":"http://gateway.marvel.com/v1/public/series/11665","name":"Black Panther: The Most Dangerous Man Alive  (2010 - 2012)"},{"resourceURI":"http://gateway.marvel.com/v1/public/series/449","name":"Daredevil (1998 - 2011)"},{"resourceURI":"http://gateway.marvel.com/v1/public/series/2002","name":"Daredevil (1963 - 1998)"},{"resourceURI":"http://gateway.marvel.com/v1/public/series/181","name":"Daredevil Vol. 6: Lowlife (2003)"},{"resourceURI":"http://gateway.marvel.com/v1/public/series/229","name":"Daredevil Vol. 7: Hardcore (2003)"},{"resourceURI":"http://gateway.marvel.com/v1/public/series/5701","name":"Deadpool (2008 - 2012)"},{"resourceURI":"http://gateway.marvel.com/v1/public/series/2005","name":"Deadpool (1997 - 2002)"},{"resourceURI":"http://gateway.marvel.com/v1/public/series/14383","name":"Essential Punisher Vol. 2 TPB (All-New Edition) (2011 - Present)"},{"resourceURI":"http://gateway.marvel.com/v1/public/series/2271","name":"Peter Parker, the Spectacular Spider-Man (1976 - 1998)"}],"returned":12},"stories":{"available":26,"collectionURI":"http://gateway.marvel.com/v1/public/characters/1010369/stories","items":[{"resourceURI":"http://gateway.marvel.com/v1/public/stories/16065","name":"Heart Attack !","type":"cover"},{"resourceURI":"http://gateway.marvel.com/v1/public/stories/16067","name":"A Love Story","type":"cover"},{"resourceURI":"http://gateway.marvel.com/v1/public/stories/16075","name":"Go Get 'Im Boys !","type":"cover"},{"resourceURI":"http://gateway.marvel.com/v1/public/stories/16079","name":"The Final Triumph of Typhoid Mary !","type":"cover"},{"resourceURI":"http://gateway.marvel.com/v1/public/stories/16159","name":"Last Rites Part 1: The Termination of Typhoid !","type":"cover"},{"resourceURI":"http://gateway.marvel.com/v1/public/stories/24523","name":"Deadpool (1997) #10","type":"interiorStory"},{"resourceURI":"http://gateway.marvel.com/v1/public/stories/24531","name":"Deadpool (1997) #12","type":"interiorStory"},{"resourceURI":"http://gateway.marvel.com/v1/public/stories/24534","name":"Deadpool (1997) #13","type":"interiorStory"},{"resourceURI":"http://gateway.marvel.com/v1/public/stories/24536","name":"Deadpool (1997) #14","type":"interiorStory"},{"resourceURI":"http://gateway.marvel.com/v1/public/stories/24626","name":"Deadpool (1997) #6","type":"interiorStory"},{"resourceURI":"http://gateway.marvel.com/v1/public/stories/24639","name":"Deadpool (1997) #7","type":"interiorStory"},{"resourceURI":"http://gateway.marvel.com/v1/public/stories/24642","name":"Deadpool (1997) #8","type":"interiorStory"},{"resourceURI":"http://gateway.marvel.com/v1/public/stories/29832","name":"Typhoid Massacre!","type":"cover"},{"resourceURI":"http://gateway.marvel.com/v1/public/stories/32016","name":"Hardcore Part 1","type":"cover"},{"resourceURI":"http://gateway.marvel.com/v1/public/stories/32018","name":"Hardcore Part 1","type":"interiorStory"},{"resourceURI":"http://gateway.marvel.com/v1/public/stories/32021","name":"Hardcore Part 2","type":"interiorStory"},{"resourceURI":"http://gateway.marvel.com/v1/public/stories/32024","name":"Hardcore Part 3","type":"interiorStory"},{"resourceURI":"http://gateway.marvel.com/v1/public/stories/53156","name":"Avengers: The Initiative (2007) #23 - Int","type":"interiorStory"},{"resourceURI":"http://gateway.marvel.com/v1/public/stories/53550","name":"Avengers: The Initiative (2007) #24","type":"cover"},{"resourceURI":"http://gateway.marvel.com/v1/public/stories/53551","name":"Avengers: The Initiative (2007) #24 - Int","type":"interiorStory"}],"returned":20},"events":{"available":1,"collectionURI":"http://gateway.marvel.com/v1/public/characters/1010369/events","items":[{"resourceURI":"http://gateway.marvel.com/v1/public/events/318","name":"Dark Reign"}],"returned":1},"urls":[{"type":"detail","url":"http://marvel.com/comics/characters/1010369/typhoid_mary?utm_campaign=apiRef&utm_source=51053776bff9f684b08a41a47734167b"},{"type":"wiki","url":"http://marvel.com/universe/Typhoid_Mary?utm_campaign=apiRef&utm_source=51053776bff9f684b08a41a47734167b"}]},{"id":1009680,"name":"Tyrannus","description":"","modified":"2011-05-24T16:32:42-0400","thumbnail":{"path":"http://i.annihil.us/u/prod/marvel/i/mg/b/40/image_not_available","extension":"jpg"},"resourceURI":"http://gateway.marvel.com/v1/public/characters/1009680","comics":{"available":10,"collectionURI":"http://gateway.marvel.com/v1/public/characters/1009680/comics","items":[{"resourceURI":"http://gateway.marvel.com/v1/public/comics/15572","name":"Fantastic Four (1998) #50"},{"resourceURI":"http://gateway.marvel.com/v1/public/comics/29830","name":"Incredible Hulks (2009) #605 (DJURDJEVIC 70TH ANNIVERSARY VARIANT)"},{"resourceURI":"http://gateway.marvel.com/v1/public/comics/36044","name":"Incredible Hulks (2009) #630"},{"resourceURI":"http://gateway.marvel.com/v1/public/comics/3435","name":"Marvel Masterworks: The Incredible Hulk Vol.3 (Hardcover)"},{"resourceURI":"http://gateway.marvel.com/v1/public/comics/2218","name":"Marvel Masterworks: The X-Men Vol. (Hardcover)"},{"resourceURI":"http://gateway.marvel.com/v1/public/comics/1377","name":"Marvel Masterworks: The X-Men Vol. 4 (Hardcover)"},{"resourceURI":"http://gateway.marvel.com/v1/public/comics/11428","name":"Tales to Astonish (1959) #81"},{"resourceURI":"http://gateway.marvel.com/v1/public/comics/12482","name":"Uncanny X-Men (1963) #34"},{"resourceURI":"http://gateway.marvel.com/v1/public/comics/12492","name":"Uncanny X-Men (1963) #43"},{"resourceURI":"http://gateway.marvel.com/v1/public/comics/12535","name":"Uncanny X-Men (1963) #82"}],"returned":10},"series":{"available":7,"collectionURI":"http://gateway.marvel.com/v1/public/characters/1009680/series","items":[{"resourceURI":"http://gateway.marvel.com/v1/public/series/421","name":"Fantastic Four (1998 - 2012)"},{"resourceURI":"http://gateway.marvel.com/v1/public/series/8842","name":"Incredible Hulks (2009 - 2011)"},{"resourceURI":"http://gateway.marvel.com/v1/public/series/1671","name":"Marvel Masterworks: The Incredible Hulk Vol.3 (2006)"},{"resourceURI":"http://gateway.marvel.com/v1/public/series/1508","name":"Marvel Masterworks: The X-Men Vol. (2005)"},{"resourceURI":"http://gateway.marvel.com/v1/public/series/1364","name":"Marvel Masterworks: The X-Men Vol. 4 (2004)"},{"resourceURI":"http://gateway.marvel.com/v1/public/series/2080","name":"Tales to Astonish (1959 - 1968)"},{"resourceURI":"http://gateway.marvel.com/v1/public/series/2258","name":"Uncanny X-Men (1963 - 2011)"}],"returned":7},"stories":{"available":7,"collectionURI":"http://gateway.marvel.com/v1/public/characters/1009680/stories","items":[{"resourceURI":"http://gateway.marvel.com/v1/public/stories/12334","name":"The Stage Is Set!","type":"interiorStory"},{"resourceURI":"http://gateway.marvel.com/v1/public/stories/15517","name":"Cover #15517","type":"cover"},{"resourceURI":"http://gateway.marvel.com/v1/public/stories/15544","name":"Call Him...Cyclops!","type":"interiorStory"},{"resourceURI":"http://gateway.marvel.com/v1/public/stories/15655","name":"Cover #15655","type":"cover"},{"resourceURI":"http://gateway.marvel.com/v1/public/stories/31829","name":"So Shall It Be!","type":"interiorStory"},{"resourceURI":"http://gateway.marvel.com/v1/public/stories/79774","name":"Interior #79774","type":"interiorStory"},{"resourceURI":"http://gateway.marvel.com/v1/public/stories/94787","name":"Incredible Hulks (2009) #605, DJURDJEVIC 70TH ANNIVERSARY VARIANT","type":"cover"}],"returned":7},"events":{"available":0,"collectionURI":"http://gateway.marvel.com/v1/public/characters/1009680/events","items":[],"returned":0},"urls":[{"type":"detail","url":"http://marvel.com/comics/characters/1009680/tyrannus?utm_campaign=apiRef&utm_source=51053776bff9f684b08a41a47734167b"}]},{"id":1011315,"name":"U-Foes","description":"","modified":"1969-12-31T19:00:00-0500","thumbnail":{"path":"http://i.annihil.us/u/prod/marvel/i/mg/8/a0/4c002e56c5cd1","extension":"jpg"},"resourceURI":"http://gateway.marvel.com/v1/public/characters/1011315","comics":{"available":0,"collectionURI":"http://gateway.marvel.com/v1/public/characters/1011315/comics","items":[],"returned":0},"series":{"available":0,"collectionURI":"http://gateway.marvel.com/v1/public/characters/1011315/series","items":[],"returned":0},"stories":{"available":0,"collectionURI":"http://gateway.marvel.com/v1/public/characters/1011315/stories","items":[],"returned":0},"events":{"available":0,"collectionURI":"http://gateway.marvel.com/v1/public/characters/1011315/events","items":[],"returned":0},"urls":[{"type":"detail","url":"http://marvel.com/comics/characters/1011315/u-foes?utm_campaign=apiRef&utm_source=51053776bff9f684b08a41a47734167b"},{"type":"wiki","url":"http://marvel.com/universe/U-Foes?utm_campaign=apiRef&utm_source=51053776bff9f684b08a41a47734167b"}]},{"id":1009681,"name":"U-Go Girl","description":"After a failed attempt at starting an acting career, Edie Sawyer turned to a life of crime until she learned of a new media savvy team of superhuman mutants named X-Force, and she decided to become a superhero.","modified":"1969-12-31T19:00:00-0500","thumbnail":{"path":"http://i.annihil.us/u/prod/marvel/i/mg/8/a0/4c003a91d4fe1","extension":"jpg"},"resourceURI":"http://gateway.marvel.com/v1/public/characters/1009681","comics":{"available":14,"collectionURI":"http://gateway.marvel.com/v1/public/characters/1009681/comics","items":[{"resourceURI":"http://gateway.marvel.com/v1/public/comics/17961","name":"X-Force (1991) #116"},{"resourceURI":"http://gateway.marvel.com/v1/public/comics/17962","name":"X-Force (1991) #117"},{"resourceURI":"http://gateway.marvel.com/v1/public/comics/17963","name":"X-Force (1991) #118"},{"resourceURI":"http://gateway.marvel.com/v1/public/comics/17964","name":"X-Force (1991) #119"},{"resourceURI":"http://gateway.marvel.com/v1/public/comics/17966","name":"X-Force (1991) #120"},{"resourceURI":"http://gateway.marvel.com/v1/public/comics/17967","name":"X-Force (1991) #121"},{"resourceURI":"http://gateway.marvel.com/v1/public/comics/17968","name":"X-Force (1991) #122"},{"resourceURI":"http://gateway.marvel.com/v1/public/comics/17969","name":"X-Force (1991) #123"},{"resourceURI":"http://gateway.marvel.com/v1/public/comics/17970","name":"X-Force (1991) #124"},{"resourceURI":"http://gateway.marvel.com/v1/public/comics/17971","name":"X-Force (1991) #125"},{"resourceURI":"http://gateway.marvel.com/v1/public/comics/17972","name":"X-Force (1991) #126"},{"resourceURI":"http://gateway.marvel.com/v1/public/comics/17973","name":"X-Force (1991) #127"},{"resourceURI":"http://gateway.marvel.com/v1/public/comics/17974","name":"X-Force (1991) #128"},{"resourceURI":"http://gateway.marvel.com/v1/public/comics/1028","name":"X-Force: Famous, Mutant & Mortal (Hardcover)"}],"returned":14},"series":{"available":2,"collectionURI":"http://gateway.marvel.com/v1/public/characters/1009681/series","items":[{"resourceURI":"http://gateway.marvel.com/v1/public/series/3633","name":"X-Force (1991 - 2004)"},{"resourceURI":"http://gateway.marvel.com/v1/public/series/88","name":"X-Force: Famous, Mutant & Mortal (2003)"}],"returned":2},"stories":{"available":24,"collectionURI":"http://gateway.marvel.com/v1/public/characters/1009681/stories","items":[{"resourceURI":"http://gateway.marvel.com/v1/public/stories/38198","name":"Cover #38198","type":"cover"},{"resourceURI":"http://gateway.marvel.com/v1/public/stories/38199","name":"Exit Wounds","type":"interiorStory"},{"resourceURI":"http://gateway.marvel.com/v1/public/stories/38200","name":"Cover #38200","type":"cover"},{"resourceURI":"http://gateway.marvel.com/v1/public/stories/38201","name":"Mister Sensitive","type":"interiorStory"},{"resourceURI":"http://gateway.marvel.com/v1/public/stories/38202","name":"Cover #38202","type":"cover"},{"resourceURI":"http://gateway.marvel.com/v1/public/stories/38203","name":"And Then There Were Six","type":"interiorStory"},{"resourceURI":"http://gateway.marvel.com/v1/public/stories/38204","name":"Cover #38204","type":"cover"},{"resourceURI":"http://gateway.marvel.com/v1/public/stories/38205","name":"What's One Life?","type":"interiorStory"},{"resourceURI":"http://gateway.marvel.com/v1/public/stories/38209","name":"Snikt!","type":"interiorStory"},{"resourceURI":"http://gateway.marvel.com/v1/public/stories/38210","name":"Cover #38210","type":"cover"},{"resourceURI":"http://gateway.marvel.com/v1/public/stories/38211","name":"Lacuna: Part One: Captain Coconut","type":"interiorStory"},{"resourceURI":"http://gateway.marvel.com/v1/public/stories/38212","name":"Cover #38212","type":"cover"},{"resourceURI":"http://gateway.marvel.com/v1/public/stories/38213","name":"Lacuna: Part Two: Larry King Has the Flu","type":"interiorStory"},{"resourceURI":"http://gateway.marvel.com/v1/public/stories/38214","name":"Cover #38214","type":"cover"},{"resourceURI":"http://gateway.marvel.com/v1/public/stories/38215","name":"Tick Tock","type":"interiorStory"},{"resourceURI":"http://gateway.marvel.com/v1/public/stories/38217","name":"Cover #38217","type":"cover"},{"resourceURI":"http://gateway.marvel.com/v1/public/stories/38218","name":"Edie and Guy Finally Do It","type":"interiorStory"},{"resourceURI":"http://gateway.marvel.com/v1/public/stories/38219","name":"Cover #38219","type":"cover"},{"resourceURI":"http://gateway.marvel.com/v1/public/stories/38220","name":"One of Us","type":"interiorStory"},{"resourceURI":"http://gateway.marvel.com/v1/public/stories/38222","name":"As I Die Lying","type":"interiorStory"}],"returned":20},"events":{"available":0,"collectionURI":"http://gateway.marvel.com/v1/public/characters/1009681/events","items":[],"returned":0},"urls":[{"type":"detail","url":"http://marvel.com/comics/characters/1009681/u-go_girl?utm_campaign=apiRef&utm_source=51053776bff9f684b08a41a47734167b"},{"type":"wiki","url":"http://marvel.com/universe/U-Go_Girl?utm_campaign=apiRef&utm_source=51053776bff9f684b08a41a47734167b"}]}]}}